odoo/addons/stock_picking_return_refund_option/README.rst
odoo/addons/stock_picking_return_refund_option/__init__.py
odoo/addons/stock_picking_return_refund_option/__manifest__.py
odoo/addons/stock_picking_return_refund_option/i18n/ca.po
odoo/addons/stock_picking_return_refund_option/i18n/es.po
odoo/addons/stock_picking_return_refund_option/i18n/it.po
odoo/addons/stock_picking_return_refund_option/i18n/stock_picking_return_refund_option.pot
odoo/addons/stock_picking_return_refund_option/models/__init__.py
odoo/addons/stock_picking_return_refund_option/models/stock_move.py
odoo/addons/stock_picking_return_refund_option/models/stock_picking.py
odoo/addons/stock_picking_return_refund_option/readme/CONTRIBUTORS.md
odoo/addons/stock_picking_return_refund_option/readme/DESCRIPTION.md
odoo/addons/stock_picking_return_refund_option/readme/INSTALL.md
odoo/addons/stock_picking_return_refund_option/readme/USAGE.md
odoo/addons/stock_picking_return_refund_option/static/description/icon.png
odoo/addons/stock_picking_return_refund_option/static/description/index.html
odoo/addons/stock_picking_return_refund_option/tests/__init__.py
odoo/addons/stock_picking_return_refund_option/tests/test_stock_picking_return_refund_options.py
odoo/addons/stock_picking_return_refund_option/views/stock_picking_view.xml
odoo_addon_stock_picking_return_refund_option-18.0.1.0.0.2.dist-info/METADATA
odoo_addon_stock_picking_return_refund_option-18.0.1.0.0.2.dist-info/WHEEL
odoo_addon_stock_picking_return_refund_option-18.0.1.0.0.2.dist-info/top_level.txt
odoo_addon_stock_picking_return_refund_option-18.0.1.0.0.2.dist-info/RECORD
